datacenter_utils/__init__.py
datacenter_utils/alert.py
datacenter_utils/aws_s3.py
datacenter_utils/logger.py
datacenter_utils/mongo_common.py
datacenter_utils/mysql_common.py
datacenter_utils/pgsql_common.py
datacenter_utils/redis_common.py
datacenter_utils-0.2.24.dist-info/LICENSE.txt
datacenter_utils-0.2.24.dist-info/METADATA
datacenter_utils-0.2.24.dist-info/WHEEL
datacenter_utils-0.2.24.dist-info/top_level.txt
datacenter_utils-0.2.24.dist-info/zip-safe
datacenter_utils-0.2.24.dist-info/RECORD
