Metadata-Version: 2.1
Name: datacenter-utils
Version: 0.2.24
Summary: datacenter_utils
Home-page: UNKNOWN
Author: Wang Sheng
Author-email: jayed008@163.com
License: MIT
Platform: UNKNOWN
Classifier: Intended Audience :: Developers
Classifier: License :: OSI Approved :: MIT License
Classifier: Operating System :: MacOS
Classifier: Operating System :: Microsoft
Classifier: Operating System :: POSIX
Classifier: Operating System :: Unix
Classifier: Topic :: Software Development :: Libraries :: Python Modules
Classifier: Programming Language :: Python :: 3.7
Classifier: Programming Language :: Python :: 3.8
License-File: LICENSE.txt
Requires-Dist: pandas
Requires-Dist: numpy
Requires-Dist: redis
Requires-Dist: pymongo
Requires-Dist: boto3
Requires-Dist: python-dateutil
Requires-Dist: psycopg2-binary (~=2.8.6)
Requires-Dist: pyyaml
Requires-Dist: requests
